{"date":"Sat, 09 Mar 2019 12:59:54 GMT","text":"Kontakt Formular Fenster schließen Rufen Sie uns an! Senden Sie uns eine E-Mail Auf der Karte anzeigen Startseite über uns Menu Kontakt Tagesmenü Unser Mittagsmenü wird täglich für Sie frisch zubereitet! Jede Woche bieten wir ein abwechslungsreiches Angebot, (inkl. Tagessuppe oder Tagessalat und Dessert) Weinkarte Datei herunterladen Menukarte Datei herunterladen Pizzakarte Datei herunterladen Startseite über uns Menu Kontakt","encoding":"UTF-8","title":"Menu - La Forchetta Schaffhausen","url":"http:\/\/www.la-forchetta-schaffhausen.ch\/menu.shtml","content":"<!DOCTYPE html>\n<html  lang=\"de\">\n<head>\n\t\t<meta http-equiv=\"Content-Type\" content=\"text\/html; charset=UTF-8\" \/>\n<meta name=\"viewport\" content=\"width=device-width, initial-scale=1, maximum-scale=1\" \/>\n<meta property=\"og:image\" content=\"\/var\/m_6\/6f\/6f1\/64534\/7061688-la Cucina.JPG\" \/>\n<meta property=\"og:title\" content=\"Menu\" \/>\n<meta name=\"generator\" content=\"Websplanet\" \/>\n<meta name=\"robots\" content=\"index,follow\" \/>\n<meta property=\"og:url\" content=\"http:\/\/www.la-forchetta-schaffhausen.ch\/menu\" \/>\t<title>Menu - La Forchetta Schaffhausen<\/title>\t<link href=\"\/templates\/resellers\/7\/favicon.ico?v=1505285483\" rel=\"SHORTCUT ICON\" type=\"image\/x-icon\" \/>\n<link href=\"\/css\/widgets\/concat_widget.min.css?v=6.6.7.2.41064\" media=\"screen\" rel=\"stylesheet\" type=\"text\/css\" \/>\n<link href=\"\/templates\/creator\/m_5\/5f\/5f9\/110\/css\/main.min.css?v=1483633815\" media=\"screen\" rel=\"stylesheet\" type=\"text\/css\" id=\"template-grid\" \/>\n<link href=\"\/templates\/creator\/m_5\/5f\/5f9\/110\/css\/style.min.css?v=1483633815\" media=\"screen\" rel=\"stylesheet\" type=\"text\/css\" id=\"template-skin\" \/>\n<link href=\"http:\/\/www.la-forchetta-schaffhausen.ch\/menu\" rel=\"canonical\" \/>\t\t\n\t<script type=\"text\/javascript\" src=\"https:\/\/ajax.googleapis.com\/ajax\/libs\/jquery\/1.7.1\/jquery.min.js?v=6.6.7.2.41064\"><\/script>\n<script type=\"text\/javascript\">\n    \/\/<!--\n       (function(i,s,o,g,r,a,m){i['GoogleAnalyticsObject']=r;i[r]=i[r]||function(){\r\n  (i[r].q=i[r].q||[]).push(arguments)},i[r].l=1*new Date();a=s.createElement(o),\r\n  m=s.getElementsByTagName(o)[0];a.async=1;a.src=g;m.parentNode.insertBefore(a,m)\r\n  })(window,document,'script','\/\/www.google-analytics.com\/analytics.js','ga');\r\n\r\n\tvar gaSettings = {\r\n\t  siteOwnerTrackingCode: false,\r\n\t\tresellerTrackingCode: false,\r\n\t\tresellerTrackerName: 'resellerTracker',\r\n\t\tsiteOwnerTrackerName: 'siteOwnerTracker'\r\n\t};\t\r\n  \r\n \r\n  \r\n      gaSettings.resellerTrackingCode = true;\r\n\r\n    ga('create', 'UA-65453061-1', 'auto', {'name': gaSettings.resellerTrackerName});  \r\n    ga(gaSettings.resellerTrackerName+'.send', 'pageview');\r\n\r\n     \r\n\r\n    \/\/-->\n<\/script>\n\t<style>.free-text-image .freetext-image .image_wrapper{display:block;}<\/style>\n\t\n\t<link type=\"text\/css\" href=\"\/css\/skeleton.css\" rel=\"stylesheet\">\r\n<link href='http:\/\/fonts.googleapis.com\/css?family=Fjalla+One' rel='stylesheet' type='text\/css'>\r\n<script type=\"text\/javascript\" src=\"\/templates\/creator\/m_5\/5f\/5f9\/110\/assets\/wp-menu.js?v=1483633815\"><\/script>\r\n<script type=\"text\/javascript\" src=\"\/templates\/creator\/m_5\/5f\/5f9\/110\/assets\/respond.min.js?v=1483633815\"><\/script>\r\n<script type=\"text\/javascript\" src=\"\/templates\/creator\/m_5\/5f\/5f9\/110\/assets\/slide.js?v=1483633815\"><\/script>\r\n\r\n<!--[if lt IE 9]>\r\n<script src=\"http:\/\/html5shim.googlecode.com\/svn\/trunk\/html5.js\"><\/script>\r\n<![endif]-->\r\n<script type=\"text\/javascript\">\r\n\t\t\/\/label of menu button on mobile version\r\n\t\tvar config = {\r\n\t\t\tnavigation: \"Navigation\"\r\n\t\t};\r\n\t<\/script>\r\n<style type=\"text\/css\" media=\"screen\">\n<!--\n\n-->\n<\/style><\/head>\r\n<body>\r\n  <!-- Panel -->\r\n\r\n  <div id=\"fixed_mobile_action\">\r\n    <div id=\"toppanel\" class=\"ios5\">\r\n        <!-- The tab on top --> \r\n      <div class=\"tab\">\r\n        <ul class=\"mobile_action\">\r\n          <li class=\"left\">&nbsp;<\/li>\r\n          <li id=\"toggle\">\r\n            <label id=\"open\" class=\"open\">Kontakt Formular<\/label>\r\n            <label id=\"close\" style=\"display: none;\" class=\"close\">Fenster schließen<\/label>     \r\n          <\/li>\r\n          <li class=\"right\">&nbsp;<\/li>\r\n        <\/ul> \r\n      <\/div> <!-- \/ top -->\r\n\r\n      <div id=\"panel\">\r\n        <div class=\"panel-content\">\r\n          <div class=\"icon\">\r\n            <a href=\"tel:052 624 01 63\" class=\"click-phone\">Rufen Sie uns an!<\/a>\r\n          <\/div>\r\n          <div class=\"icon\">\r\n            <a href=\"mailto:info@la-forchetta-schaffhausen.ch\" class=\"click-mail\">Senden Sie uns eine E-Mail<\/a>\r\n          <\/div>\r\n          <div class=\"icon\">\r\n            <a href=\"https:\/\/maps.google.com\/maps?q=Vorstadt 58 Schaffhausen Switzerland\" class=\"click-map\">Auf der Karte anzeigen<\/a>\r\n          <\/div>\r\n\r\n        <\/div>\r\n    <\/div> \r\n\r\n\r\n      \r\n    <\/div> <!--panel -->\r\n  <\/div>\r\n  <div class=\"header sk-container\">\r\n    <div class=\"sixteen columns \">\r\n      <div class=\"logo-container\" ><a href=\"\/\" class=\"logo\"><img src=\"\/var\/m_6\/6f\/6f1\/64534\/7047123-Logo.w180.h100.JPG?1505285483\" alt=\"La Forchetta Schaffhausen\" id=\"siteMainDynLogo\" border=\"0px\" data-test=\"123\" \/><\/a> <script type=\"application\/ld+json\">\n    \t\t\t\t{\n\t\t\t\t      \"@context\": \"http:\/\/schema.org\",\n\t\t\t\t      \"@type\": \"LocalBusiness\",\n\t\t\t\t      \"url\": \"http:\/\/www.la-forchetta-schaffhausen.ch\",\n\t\t\t\t      \"logo\": \"\/var\/m_6\/6f\/6f1\/64534\/7047123-Logo.w180.h100.JPG?1505285483\"\n\t\t\t\t    }\n\t\t\t\t\t<\/script><\/div>\r\n      <nav class=\"nav\">\r\n        <ul id=\"nav\" class=\"menu_count_4 wp-menu\"><li id=\"menu_26\" class=\"first  lb_26 menu-item-home\"><a href=\"http:\/\/www.la-forchetta-schaffhausen.ch\/\" target=\"_self\" title=\"Startseite\" data-pageid=\"26\" data-act=\"canvas\" data-itemid=\"40\" data-cat=\"0\">Startseite<\/a> <\/li><li id=\"menu_816503\" class=\" lb_816503 menu-item-toppage\"><a href=\"http:\/\/www.la-forchetta-schaffhausen.ch\/über-uns.shtml\" target=\"_self\" title=\"über uns\" data-pageid=\"816503\" data-act=\"canvas\" data-itemid=\"872107\" data-cat=\"0\">über uns<\/a> <\/li><li id=\"menu_816504\" class=\"current  lb_816504 menu-item-toppage\"><a href=\"http:\/\/www.la-forchetta-schaffhausen.ch\/menu.shtml\" target=\"_self\" title=\"Menu\" data-pageid=\"816504\" data-act=\"canvas\" data-itemid=\"872108\" data-cat=\"0\">Menu<\/a> <\/li><li id=\"menu_816247\" class=\"last lb_816247 menu-item-toppage\"><a href=\"http:\/\/www.la-forchetta-schaffhausen.ch\/kontakt.shtml\" target=\"_self\" title=\"Kontakt\" data-pageid=\"816247\" data-act=\"canvas\" data-itemid=\"871832\" data-cat=\"0\">Kontakt<\/a> <\/li><\/ul> \r\n      <\/nav>\r\n    <\/div>\r\n  <\/div>\r\n  <div class=\"sk-container skinAlign\">\r\n    <!-- START HEADER IMAGE -->\r\n      <div id=\"header-image\" class=\"sixteen columns \">\r\n        <div class=\"headerimage\">\r\n          <div id=\"header-image-wrapper-1\"><img src=\"\/var\/m_6\/6f\/6f1\/64534\/7061688-la Cucina.JPG\" id=\"siteMainDynHeaderImage1\" style=\"border:0px\" \/><\/div>        <\/div>\r\n              <\/div>\r\n      <!-- END HEADER IMAGE -->\r\n    <div id=\"content\" class=\"sixteen columns skinBg\">\r\n      <!-- START CONTENT -->\r\n      <div class=\"content-data\"> \r\n      \t<div id=\"searchResults\"><\/div>        <div id=\"wp_content_data\"><div class=\"vertical\" style=\"width: 100%;\"><div class=\"widget-wrapper widget-element free-text diy-resizable \">\n\n\t\t<div id=\"widget-id-9445738\" \n\t\tclass=\"widget-body \" style=\"\">\n\t\t<div class=\"freetextarea\">\t\n\t<div><h1>Tagesmenü<\/h1><br>Unser Mittagsmenü wird täglich für Sie frisch zubereitet!<br>Jede Woche bieten wir ein abwechslungsreiches Angebot, (inkl. Tagessuppe oder Tagessalat und Dessert)<br><br><br><\/div><div><br><\/div><\/div>\n<div class=\"clear\"><\/div>\t<\/div>\n<\/div>\n\n\n<div class=\"widget-wrapper widget-element files diy-resizable \">\n\n\t\t<div id=\"widget-id-9597449\" \n\t\tclass=\"widget-body \" style=\"\">\n\t\t<div class=\"widget-wrapper files-widget-wrapper align-left\">\r\n\t<div class=\"files-widget-icon\"><img src=\"\/gfx\/fileTypes\/pdf.png\" alt=\"Datei\"\/><\/div>\r\n\t<div class=\"files-widget-description\">\r\n\t\t<p>Weinkarte<\/p>\r\n\t\t<a href=\"\/var\/m_6\/6f\/6f1\/64534\/7228259-Weinkarte.pdf?download\">Datei herunterladen<\/a>\r\n\t<\/div>\r\n\t<div class=\"clear\"><\/div>\r\n<\/div>\t<\/div>\n<\/div>\n\n\n<div class=\"widget-wrapper widget-element files diy-resizable \">\n\n\t\t<div id=\"widget-id-9445739\" \n\t\tclass=\"widget-body \" style=\"\">\n\t\t<div class=\"widget-wrapper files-widget-wrapper align-left\">\r\n\t<div class=\"files-widget-icon\"><img src=\"\/gfx\/fileTypes\/pdf.png\" alt=\"Datei\"\/><\/div>\r\n\t<div class=\"files-widget-description\">\r\n\t\t<p>Menukarte<\/p>\r\n\t\t<a href=\"\/var\/m_6\/6f\/6f1\/64534\/7064629-Menukarte.pdf?download\">Datei herunterladen<\/a>\r\n\t<\/div>\r\n\t<div class=\"clear\"><\/div>\r\n<\/div>\t<\/div>\n<\/div>\n\n\n<div class=\"widget-wrapper widget-element files diy-resizable \">\n\n\t\t<div id=\"widget-id-9445740\" \n\t\tclass=\"widget-body \" style=\"\">\n\t\t<div class=\"widget-wrapper files-widget-wrapper align-left\">\r\n\t<div class=\"files-widget-icon\"><img src=\"\/gfx\/fileTypes\/pdf.png\" alt=\"Datei\"\/><\/div>\r\n\t<div class=\"files-widget-description\">\r\n\t\t<p>Pizzakarte <\/p>\r\n\t\t<a href=\"\/var\/m_6\/6f\/6f1\/64534\/7064631-Pizzakarte.pdf?download\">Datei herunterladen<\/a>\r\n\t<\/div>\r\n\t<div class=\"clear\"><\/div>\r\n<\/div>\t<\/div>\n<\/div>\n\n\n<div class=\"horizontal clearfix\" style=\"\"><div class=\"diy-splitter-inner clearfix\"><div class=\"vertical\" style=\"width: 25%;\"><div class=\"widget-wrapper widget-element free-image diy-resizable \">\n\n\t\t<div id=\"widget-id-9458847\" \n\t\tclass=\"widget-body \" style=\"\">\n\t\t<div class=\"freetext-image modify-size\" style=\" width:100%; float:left; text-align:left;\">\r\n    <div class=\"image_wrapper diy-icss-target\" style=\"\">    \r\n                <div class=\"diy-fi-container diy-fi-effect-\">\r\n                    <img id=\"7067864\" \r\n                         style=\"width:100%\" \r\n                         data-original=\"\/var\/m_6\/6f\/6f1\/64534\/7067864-IMG_0232.JPG\" \r\n                         alt=\"\"\r\n                         class=\"image lazy\"\r\n                         \/>\r\n                        <\/div>\r\n                    <\/div>\r\n    <\/div>\r\n<div class=\"clear\"><\/div>\r\n\r\n\t<\/div>\n<\/div>\n\n\n<\/div><div class=\"vertical\" style=\"width: 25%;\"><div class=\"widget-wrapper widget-element free-image diy-resizable \">\n\n\t\t<div id=\"widget-id-9458848\" \n\t\tclass=\"widget-body \" style=\"\">\n\t\t<div class=\"freetext-image \" style=\" float:left; text-align:left;\">\r\n    <div class=\"image_wrapper diy-icss-target\" style=\"\">    \r\n                <div class=\"diy-fi-container diy-fi-effect-\">\r\n                    <img id=\"7067866\" \r\n                         style=\"max-width:100%\" \r\n                         data-original=\"\/var\/m_6\/6f\/6f1\/64534\/7067866-IMG_0233.JPG\" \r\n                         alt=\"\"\r\n                         class=\"image lazy\"\r\n                         \/>\r\n                        <\/div>\r\n                    <\/div>\r\n    <\/div>\r\n<div class=\"clear\"><\/div>\r\n\r\n\t<\/div>\n<\/div>\n\n\n<\/div><div class=\"vertical\" style=\"width: 25%;\"><div class=\"widget-wrapper widget-element free-image diy-resizable \">\n\n\t\t<div id=\"widget-id-9458849\" \n\t\tclass=\"widget-body \" style=\"\">\n\t\t<div class=\"freetext-image \" style=\" float:left; text-align:left;\">\r\n    <div class=\"image_wrapper diy-icss-target\" style=\"\">    \r\n                <div class=\"diy-fi-container diy-fi-effect-\">\r\n                    <img id=\"7067867\" \r\n                         style=\"max-width:100%\" \r\n                         data-original=\"\/var\/m_6\/6f\/6f1\/64534\/7067867-IMG_0234.JPG\" \r\n                         alt=\"\"\r\n                         class=\"image lazy\"\r\n                         \/>\r\n                        <\/div>\r\n                    <\/div>\r\n    <\/div>\r\n<div class=\"clear\"><\/div>\r\n\r\n\t<\/div>\n<\/div>\n\n\n<\/div><div class=\"vertical\" style=\"width: 25%;\"><div class=\"widget-wrapper widget-element free-image diy-resizable \">\n\n\t\t<div id=\"widget-id-9458850\" \n\t\tclass=\"widget-body \" style=\"\">\n\t\t<div class=\"freetext-image \" style=\" float:left; text-align:left;\">\r\n    <div class=\"image_wrapper diy-icss-target\" style=\"\">    \r\n                <div class=\"diy-fi-container diy-fi-effect-\">\r\n                    <img id=\"7067868\" \r\n                         style=\"max-width:100%\" \r\n                         data-original=\"\/var\/m_6\/6f\/6f1\/64534\/7067868-IMG_0236.JPG\" \r\n                         alt=\"\"\r\n                         class=\"image lazy\"\r\n                         \/>\r\n                        <\/div>\r\n                    <\/div>\r\n    <\/div>\r\n<div class=\"clear\"><\/div>\r\n\r\n\t<\/div>\n<\/div>\n\n\n<\/div><\/div><\/div><div class=\"clearfix\"><\/div><div class=\"horizontal clearfix\" style=\"\"><div class=\"diy-splitter-inner clearfix\"><div class=\"vertical\" style=\"width: 25%;\"><div class=\"widget-wrapper widget-element free-image diy-resizable \">\n\n\t\t<div id=\"widget-id-9458851\" \n\t\tclass=\"widget-body \" style=\"\">\n\t\t<div class=\"freetext-image \" style=\" float:left; text-align:left;\">\r\n    <div class=\"image_wrapper diy-icss-target\" style=\"\">    \r\n                <div class=\"diy-fi-container diy-fi-effect-\">\r\n                    <img id=\"7067869\" \r\n                         style=\"max-width:100%\" \r\n                         data-original=\"\/var\/m_6\/6f\/6f1\/64534\/7067869-IMG_0237.JPG\" \r\n                         alt=\"\"\r\n                         class=\"image lazy\"\r\n                         \/>\r\n                        <\/div>\r\n                    <\/div>\r\n    <\/div>\r\n<div class=\"clear\"><\/div>\r\n\r\n\t<\/div>\n<\/div>\n\n\n<\/div><div class=\"vertical\" style=\"width: 25%;\"><div class=\"widget-wrapper widget-element free-image diy-resizable \">\n\n\t\t<div id=\"widget-id-9458852\" \n\t\tclass=\"widget-body \" style=\"\">\n\t\t<div class=\"freetext-image \" style=\" float:left; text-align:left;\">\r\n    <div class=\"image_wrapper diy-icss-target\" style=\"\">    \r\n                <div class=\"diy-fi-container diy-fi-effect-\">\r\n                    <img id=\"7067870\" \r\n                         style=\"max-width:100%\" \r\n                         data-original=\"\/var\/m_6\/6f\/6f1\/64534\/7067870-IMG_0238.JPG\" \r\n                         alt=\"\"\r\n                         class=\"image lazy\"\r\n                         \/>\r\n                        <\/div>\r\n                    <\/div>\r\n    <\/div>\r\n<div class=\"clear\"><\/div>\r\n\r\n\t<\/div>\n<\/div>\n\n\n<\/div><div class=\"vertical\" style=\"width: 25%;\"><div class=\"widget-wrapper widget-element free-image diy-resizable \">\n\n\t\t<div id=\"widget-id-9458853\" \n\t\tclass=\"widget-body \" style=\"\">\n\t\t<div class=\"freetext-image modify-size\" style=\" width:100%; float:left; text-align:left;\">\r\n    <div class=\"image_wrapper diy-icss-target\" style=\"\">    \r\n                <div class=\"diy-fi-container diy-fi-effect-\">\r\n                    <img id=\"7067871\" \r\n                         style=\"width:100%\" \r\n                         data-original=\"\/var\/m_6\/6f\/6f1\/64534\/7067871-IMG_0239.JPG\" \r\n                         alt=\"\"\r\n                         class=\"image lazy\"\r\n                         \/>\r\n                        <\/div>\r\n                    <\/div>\r\n    <\/div>\r\n<div class=\"clear\"><\/div>\r\n\r\n\t<\/div>\n<\/div>\n\n\n<\/div><div class=\"vertical\" style=\"width: 25%;\"><div class=\"widget-wrapper widget-element free-image diy-resizable \">\n\n\t\t<div id=\"widget-id-9458854\" \n\t\tclass=\"widget-body \" style=\"\">\n\t\t<div class=\"freetext-image modify-size\" style=\" width:99.09502262443439%; float:left; text-align:left;\">\r\n    <div class=\"image_wrapper diy-icss-target\" style=\"\">    \r\n                <div class=\"diy-fi-container diy-fi-effect-\">\r\n                    <img id=\"7067885\" \r\n                         style=\"width:100%\" \r\n                         data-original=\"\/var\/m_6\/6f\/6f1\/64534\/7067885-test6.jpg\" \r\n                         alt=\"\"\r\n                         class=\"image lazy\"\r\n                         \/>\r\n                        <\/div>\r\n                    <\/div>\r\n    <\/div>\r\n<div class=\"clear\"><\/div>\r\n\r\n\t<\/div>\n<\/div>\n\n\n<\/div><\/div><\/div><div class=\"clearfix\"><\/div><div class=\"horizontal clearfix\" style=\"\"><div class=\"diy-splitter-inner clearfix\"><div class=\"vertical\" style=\"width: 25%;\"><div class=\"widget-wrapper widget-element free-image diy-resizable \">\n\n\t\t<div id=\"widget-id-9458855\" \n\t\tclass=\"widget-body \" style=\"\">\n\t\t<div class=\"freetext-image \" style=\" float:left; text-align:left;\">\r\n    <div class=\"image_wrapper diy-icss-target\" style=\"\">    \r\n                <div class=\"diy-fi-container diy-fi-effect-\">\r\n                    <img id=\"7067873\" \r\n                         style=\"max-width:100%\" \r\n                         data-original=\"\/var\/m_6\/6f\/6f1\/64534\/7067873-IMG_0241.JPG\" \r\n                         alt=\"\"\r\n                         class=\"image lazy\"\r\n                         \/>\r\n                        <\/div>\r\n                    <\/div>\r\n    <\/div>\r\n<div class=\"clear\"><\/div>\r\n\r\n\t<\/div>\n<\/div>\n\n\n<\/div><div class=\"vertical\" style=\"width: 25%;\"><div class=\"widget-wrapper widget-element free-image diy-resizable \">\n\n\t\t<div id=\"widget-id-9458856\" \n\t\tclass=\"widget-body \" style=\"\">\n\t\t<div class=\"freetext-image \" style=\" float:left; text-align:left;\">\r\n    <div class=\"image_wrapper diy-icss-target\" style=\"\">    \r\n                <div class=\"diy-fi-container diy-fi-effect-\">\r\n                    <img id=\"7067874\" \r\n                         style=\"max-width:100%\" \r\n                         data-original=\"\/var\/m_6\/6f\/6f1\/64534\/7067874-IMG_0242.JPG\" \r\n                         alt=\"\"\r\n                         class=\"image lazy\"\r\n                         \/>\r\n                        <\/div>\r\n                    <\/div>\r\n    <\/div>\r\n<div class=\"clear\"><\/div>\r\n\r\n\t<\/div>\n<\/div>\n\n\n<\/div><div class=\"vertical\" style=\"width: 25%;\"><div class=\"widget-wrapper widget-element free-image diy-resizable \">\n\n\t\t<div id=\"widget-id-9458857\" \n\t\tclass=\"widget-body \" style=\"\">\n\t\t<div class=\"freetext-image \" style=\" float:left; text-align:left;\">\r\n    <div class=\"image_wrapper diy-icss-target\" style=\"\">    \r\n                <div class=\"diy-fi-container diy-fi-effect-\">\r\n                    <img id=\"7067875\" \r\n                         style=\"max-width:100%\" \r\n                         data-original=\"\/var\/m_6\/6f\/6f1\/64534\/7067875-IMG_0243.JPG\" \r\n                         alt=\"\"\r\n                         class=\"image lazy\"\r\n                         \/>\r\n                        <\/div>\r\n                    <\/div>\r\n    <\/div>\r\n<div class=\"clear\"><\/div>\r\n\r\n\t<\/div>\n<\/div>\n\n\n<\/div><div class=\"vertical\" style=\"width: 25%;\"><div class=\"widget-wrapper widget-element free-image diy-resizable \">\n\n\t\t<div id=\"widget-id-9458858\" \n\t\tclass=\"widget-body \" style=\"\">\n\t\t<div class=\"freetext-image modify-size\" style=\" width:100%; float:left; text-align:left;\">\r\n    <div class=\"image_wrapper diy-icss-target\" style=\"\">    \r\n                <div class=\"diy-fi-container diy-fi-effect-\">\r\n                    <img id=\"7067878\" \r\n                         style=\"width:100%\" \r\n                         data-original=\"\/var\/m_6\/6f\/6f1\/64534\/7067878-IMG_0230.JPG\" \r\n                         alt=\"\"\r\n                         class=\"image lazy\"\r\n                         \/>\r\n                        <\/div>\r\n                    <\/div>\r\n    <\/div>\r\n<div class=\"clear\"><\/div>\r\n\r\n\t<\/div>\n<\/div>\n\n\n<\/div><\/div><\/div><div class=\"clearfix\"><\/div><\/div><\/div>      <\/div>  \r\n      <!-- END CONTENT -->\r\n    <\/div>\r\n\r\n    <div class=\"sixteen columns\">\r\n      <div class=\"footer\">\r\n      \r\n      <div class=\"clearfix\">\r\n        <div class=\"mirrormenu\"><ul id=\"mirror-menu-module\"><li id=\"mirror_menu_td_26\" class=\"mirror_menu\"><a href=\"http:\/\/www.la-forchetta-schaffhausen.ch\/\" target=\"_self\" title=\"Startseite\" data-pageid=\"26\" data-act=\"canvas\" data-itemid=\"40\" data-cat=\"0\">Startseite<\/a><\/li><li id=\"mirror_menu_td_816503\" class=\"mirror_menu\"><a href=\"http:\/\/www.la-forchetta-schaffhausen.ch\/über-uns.shtml\" target=\"_self\" title=\"über uns\" data-pageid=\"816503\" data-act=\"canvas\" data-itemid=\"872107\" data-cat=\"0\">über uns<\/a><\/li><li id=\"mirror_menu_td_816504\" class=\"mirror_menu\"><a href=\"http:\/\/www.la-forchetta-schaffhausen.ch\/menu.shtml\" target=\"_self\" title=\"Menu\" data-pageid=\"816504\" data-act=\"canvas\" data-itemid=\"872108\" data-cat=\"0\">Menu<\/a><\/li><li id=\"mirror_menu_td_816247\" class=\"mirror_menu\"><a href=\"http:\/\/www.la-forchetta-schaffhausen.ch\/kontakt.shtml\" target=\"_self\" title=\"Kontakt\" data-pageid=\"816247\" data-act=\"canvas\" data-itemid=\"871832\" data-cat=\"0\">Kontakt<\/a><\/li><\/ul><\/div>\r\n        <div class=\"footer-text\"><p>  <\/p>\r\n<\/div>\r\n        <div class=\"languages\">\r\n              <\/div>\r\n      <\/div>\r\n      \r\n    <\/div>\r\n    <\/div>\r\n  <\/div>\n\t\t\n\t    <script type=\"text\/javascript\">\n    \/\/<!--\n    var sid = 64534;    \/\/-->\n<\/script>\n<script type=\"text\/javascript\" src=\"\/js\/functions_stripped.js?v=6.6.7.2.41064\"><\/script>\n<script type=\"text\/javascript\" src=\"\/js\/jquery.lazyload.min.js?v=6.6.7.2.41064\"><\/script>    <script type=\"application\/ld+json\">\n{\n\t\"@context\": \"http:\/\/schema.org\",\n\t\"@type\": \"LocalBusiness\",\n\t\"url\": \"http:\/\/www.la-forchetta-schaffhausen.ch\",\n\t\"name\": \"La Forchetta Schaffhausen\",\n\t\"email\": \"info@la-forchetta-schaffhausen.ch\",\n\t\"address\": {\n\t    \"@type\": \"PostalAddress\",\n\t    \"addressLocality\": \"Schaffhausen\",\n\t    \"addressRegion\": \"\",\n\t    \"addressCountry\":\"Switzerland\",\n\t    \"postalCode\":\"8200\",\n\t    \"streetAddress\": \"Vorstadt 58\"\n\t                },\n\t\"telephone\": \"052 624 01 63\",\n\t\"telephone\": \"\",\n\t\"fax\": \"\"\n}\n<\/script>\n<\/body>\n<\/html>"}